setup.py
django_js_variable_injector.egg-info/PKG-INFO
django_js_variable_injector.egg-info/SOURCES.txt
django_js_variable_injector.egg-info/dependency_links.txt
django_js_variable_injector.egg-info/entry_points.txt
django_js_variable_injector.egg-info/not-zip-safe
django_js_variable_injector.egg-info/top_level.txt
djangojs_variable_injector/djangojs_variable_injector/__init__.py
djangojs_variable_injector/djangojs_variable_injector/settings.py
djangojs_variable_injector/djangojs_variable_injector/urls.py
djangojs_variable_injector/djangojs_variable_injector/wsgi.py
djangojs_variable_injector/injector/__init__.py
djangojs_variable_injector/injector/models.py
djangojs_variable_injector/injector/views.py
djangojs_variable_injector/injector/templatetags/__init__.py
djangojs_variable_injector/injector/templatetags/js_injector.py