Metadata-Version: 1.1
Name: django-js-variable-injector
Version: 1.0.2
Summary: A (more) elegant solution for injecting Django template variables into the context of an external Javascript file
Home-page: https://github.com/steinbachr/django-js-variable-injector
Author: Bobby Steinbach
Author-email: steinbach.rj@gmail.com
License: MIT
Keywords: django js injection template variables
Platform: UNKNOWN
Classifier: Development Status :: 3 - Alpha
